icanvas
