Metadata-Version: 1.0
Name: icanvas
Version: 0.0.22
Summary: Canvas Installation Module
Home-page: http://github.com/sunlove123
Author: DeenaDhayalan
Author-email: deena.boopathy@intellectdesign.com
License: MIT
Platform: UNKNOWN
